nbsphinx_multilink/__init__.py
nbsphinx_multilink/_version.py
nbsphinx_multilink-1.4.1.dist-info/LICENSE
nbsphinx_multilink-1.4.1.dist-info/METADATA
nbsphinx_multilink-1.4.1.dist-info/WHEEL
nbsphinx_multilink-1.4.1.dist-info/top_level.txt
nbsphinx_multilink-1.4.1.dist-info/RECORD
