Metadata-Version: 2.1
Name: nbsphinx-multilink
Version: 1.4.1
Summary: A sphinx extension for including notebook files outside sphinx source root
Home-page: https://github.com/vidartf/nbsphinx-multilink
Author: Vidar Tonaas Fauske
Author-email: vidartf@gmail.com
Maintainer: Austin Raney
Maintainer-email: aaraney@crimson.ua.edu
License: BSD-3
Keywords: Interactive,Interpreter,Shell,Web
Platform: Linux
Platform: Mac OS X
Platform: Windows
Classifier: Intended Audience :: Developers
Classifier: License :: OSI Approved :: BSD License
Classifier: Programming Language :: Python
Classifier: Programming Language :: Python :: 2.7
Classifier: Programming Language :: Python :: 3
Classifier: Programming Language :: Python :: 3.4
Classifier: Programming Language :: Python :: 3.5
Classifier: Programming Language :: Python :: 3.6
Classifier: Programming Language :: Python :: 3.7
Classifier: Programming Language :: Python :: 3.8
Classifier: Programming Language :: Python :: 3.9
Requires-Dist: nbsphinx
Requires-Dist: sphinx (>=1.8)
